bysh/__init__.py
bysh/__main__.py
bysh/commands/__init__.py
bysh/commands/_abstract_command.py
bysh/commands/builtins/__init__.py
bysh/commands/builtins/cd.py
bysh/commands/builtins/dollar_interrogative.py
bysh/commands/builtins/echo.py
bysh/commands/builtins/exit_.py
bysh/commands/builtins/hash_.py
bysh/commands/builtins/help_.py
bysh/commands/builtins/nop.py
bysh/commands/builtins/pwd.py
bysh/commands/bysh/__init__.py
bysh/commands/commands/__init__.py
bysh/commands/commands/cat.py
bysh/commands/commands/cp.py
bysh/commands/commands/ls.py
bysh/commands/commands/mkdir.py
bysh/commands/commands/mv.py
bysh/commands/commands/rm.py
bysh/commands/commands/touch.py
bysh/core/__init__.py
bysh/core/bysh.py
bysh/core/shell.py
bysh/core/stdio.py
bysh/core/store.py
bysh/lib/__init__.py
bysh/lib/bashlex/__init__.py
bysh/lib/bashlex/ast.py
bysh/lib/bashlex/errors.py
bysh/lib/bashlex/flags.py
bysh/lib/bashlex/heredoc.py
bysh/lib/bashlex/parser.py
bysh/lib/bashlex/parsetab.py
bysh/lib/bashlex/shutils.py
bysh/lib/bashlex/state.py
bysh/lib/bashlex/subst.py
bysh/lib/bashlex/tokenizer.py
bysh/lib/bashlex/utils.py
bysh/lib/bashlex/yacc.py
bysh/lib/colorama/__init__.py
bysh/lib/colorama/ansi.py
bysh/lib/colorama/ansitowin32.py
bysh/lib/colorama/initialise.py
bysh/lib/colorama/win32.py
bysh/lib/colorama/winterm.py
bysh-0.0.4.dist-info/METADATA
bysh-0.0.4.dist-info/WHEEL
bysh-0.0.4.dist-info/entry_points.txt
bysh-0.0.4.dist-info/top_level.txt
bysh-0.0.4.dist-info/RECORD
