Metadata-Version: 2.1
Name: bysh
Version: 0.0.4
Summary: The unstable bash
Home-page: https://github.com/haytek/bysh
Author: haytek
Author-email: haytek34@gmail.com
License: UNKNOWN
Platform: UNKNOWN
Classifier: License :: OSI Approved :: GNU Lesser General Public License v3 (LGPLv3)
Classifier: Programming Language :: Python :: 3 :: Only
Classifier: Programming Language :: Python :: 3.7
Classifier: Programming Language :: Python :: 3.8
Requires-Python: >=3.7
